src/__init__.py
src/antenna.py
src/test.py
Fractal_Array_Antenna-1.0.dist-info/LICENSE.txt
Fractal_Array_Antenna-1.0.dist-info/METADATA
Fractal_Array_Antenna-1.0.dist-info/WHEEL
Fractal_Array_Antenna-1.0.dist-info/top_level.txt
Fractal_Array_Antenna-1.0.dist-info/RECORD
