Metadata-Version: 2.1
Name: Fractal-Array-Antenna
Version: 1.0
Summary: Array Factor Code of Fractal Array Antenna 
Home-page: UNKNOWN
Author: Dr.V.A.Sankar Ponnapalli
Author-email: vadityasankar3@gmail.com
License: UNKNOWN
Platform: UNKNOWN
Classifier: Programming Language :: Python :: 3
Classifier: License :: OSI Approved :: MIT License
Classifier: Operating System :: OS Independent
License-File: LICENSE.txt
